osais/__init__.py
osais/osais.py
osais-1.0.49.dist-info/LICENSE
osais-1.0.49.dist-info/METADATA
osais-1.0.49.dist-info/WHEEL
osais-1.0.49.dist-info/top_level.txt
osais-1.0.49.dist-info/RECORD
