Metadata-Version: 2.1
Name: osais
Version: 1.0.49
Summary: The osais Python lib for connecting AIs to OSAIS cloud
Home-page: https://github.com/incubiq/osais
Author: incubiq
Author-email: eric@incubiq.com
Keywords: osais,opensourceais
Classifier: Development Status :: 3 - Alpha
Classifier: Intended Audience :: Developers
Classifier: Programming Language :: Python :: 3
Classifier: Programming Language :: Python :: 3.6
Classifier: Programming Language :: Python :: 3.7
Classifier: Programming Language :: Python :: 3.8
Classifier: Programming Language :: Python :: 3.9
Classifier: License :: OSI Approved :: MIT License
Classifier: Operating System :: OS Independent
Requires-Python: >=3
License-File: LICENSE
Requires-Dist: asyncio (==3.4.3)
Requires-Dist: requests (>=2.25.1)
Requires-Dist: schedule (==1.1.0)
Requires-Dist: watchdog (==2.1.9)
Requires-Dist: Werkzeug (==2.2.2)
Requires-Dist: Jinja2 (==3.1.2)
Requires-Dist: boto3 (==1.26.130)
